autisticstuff/__init__.py
autisticstuff/fastapi/__init__.py
autisticstuff/fastapi/respsys/__init__.py
autisticstuff/fastapi/respsys/exceptions/__init__.py
autisticstuff/fastapi/respsys/handler.py
autisticstuff/fastapi/respsys/schemas/__init__.py
autisticstuff/fastapi/respsys/schemas/base/__init__.py
autisticstuff/fastapi/respsys/schemas/mapping_so.py
autisticstuff/fastapi/respsys/schemas/response/__init__.py
autisticstuff/fastapi/utils/__init__.py
autisticstuff/fastapi/utils/ensurevalidroles.py
autisticstuff/fastapi/utils/telegram_wa_hash.py
autisticstuff/logs/__init__.py
autisticstuff/logs/factory.py
autisticstuff/logs/intercept.py
autisticstuff/py.typed
autisticstuff/safe/__init__.py
autisticstuff/safe/aiogram.py
autisticstuff/safe/core.py
autisticstuff/safe/session.py
autisticstuff/sqla/__init__.py
autisticstuff/sqla/layers/__init__.py
autisticstuff/sqla/layers/mapping.py
autisticstuff/sqla/layers/repo.py
autisticstuff/sqla/types/__init__.py
autisticstuff/sqla/types/pjson/__init__.py
autisticstuff/sqla/types/pjson/event.py
autisticstuff/sqla/types/pjson/type.py
autisticstuff/sqla/utils/__init__.py
autisticstuff/sqla/utils/update/__init__.py
autisticstuff/sqla/utils/validate/__init__.py
autisticstuff/utils/__init__.py
autisticstuff/utils/_dev/__init__.py
autisticstuff/utils/_dev/placeholders.py
autisticstuff/utils/config/__init__.py
autisticstuff/utils/config/config.py
autisticstuff/utils/enums/__init__.py
autisticstuff/utils/enums/enums.py
autisticstuff/utils/lru/__init__.py
autisticstuff/utils/lru/object.py
autisticstuff/utils/progbars/__init__.py
autisticstuff/utils/progbars/enums.py
autisticstuff/utils/progbars/progress_bar.py
autisticstuff/utils/progbars/utils.py
autisticstuff-0.1.3.dist-info/WHEEL
autisticstuff-0.1.3.dist-info/METADATA
autisticstuff-0.1.3.dist-info/RECORD
