Metadata-Version: 2.3
Name: autisticstuff
Version: 0.1.3
Summary: Autistic stuff, either created by us, or stolen from someone on the internet
Author: plassstic, amnesiawho
Author-email: plassstic <i@apechenin.ru>, amnesiawho <ai28092005@gmail.com>
Requires-Dist: aiogram>=3.22.0
Requires-Dist: aiohttp>=3.12.15
Requires-Dist: fastapi>=0.116.1
Requires-Dist: loguru>=0.7.3
Requires-Dist: pydantic>=2.11.7
Requires-Dist: python-dotenv>=1.1.1
Requires-Dist: sqlalchemy[asyncio]>=2.0.43
Requires-Python: >=3.13
